chatady/__init__.py
chatady/chatady.py
chatady-1.1.0.dist-info/LICENSE
chatady-1.1.0.dist-info/METADATA
chatady-1.1.0.dist-info/WHEEL
chatady-1.1.0.dist-info/entry_points.txt
chatady-1.1.0.dist-info/top_level.txt
chatady-1.1.0.dist-info/RECORD
