Metadata-Version: 2.1
Name: chatady
Version: 1.1.0
Summary: A Python wrapper for the ChatADy API.
Author-email: Jernej Pregelj <contact@chatady.com>
License: MIT License
Project-URL: Homepage, https://github.com/ChatADy/chatady-python
Keywords: chatady,api,wrapper
Classifier: License :: OSI Approved :: MIT License
Classifier: Programming Language :: Python
Classifier: Programming Language :: Python :: 3
Requires-Python: >=3.6
License-File: LICENSE
Requires-Dist: requests
Provides-Extra: dev
Requires-Dist: black; extra == "dev"
Requires-Dist: bumpver; extra == "dev"
Requires-Dist: isort; extra == "dev"
Requires-Dist: pip-tools; extra == "dev"
Requires-Dist: pytest; extra == "dev"
